Workbook

Sheet Summary
A1: Hamro Mall Admin Platform – Work Breakdown Structure
A2: Based on SRS Vol.1 (Product, Attributes, Order, Vendors) and Vol.2 (Customer, Role, CMS, Settings). Hours = effort hours.
A4: Assumptions (blue = editable input)
A5: Contingency % | C5: 0.1
A6: Productive hours per person-week | C6: 35
A7: Team size (people working in parallel) | C7: 6
A8: Base effort (hrs) | C8: =WBS!M116 -> 3215
A9: Effort incl. contingency (hrs) | C9: =C8*(1+C5) -> 3536.5
A10: Person-weeks | C10: =C9/C6 -> 101.04286
A11: Indicative duration (weeks, if team works fully parallel) | C11: =C10/C7 -> 16.840476
A13: Effort by Epic
A14: ID | B14: Name | C14: Stories | D14: Frontend | E14: Backend | F14: QA | G14: DevOps | H14: Total | I14: % of total
A15: E01 | B15: Project Setup & Platform Foundation | C15: =COUNTIF(WBS!$A$2:$A$115,A15) -> 5 | D15: =SUMIFS(WBS!$I$2:$I$115,WBS!$A$2:$A$115,$A15) -> 44 | E15: =SUMIFS(WBS!$J$2:$J$115,WBS!$A$2:$A$115,$A15) -> 76 | F15: =SUMIFS(WBS!$K$2:$K$115,WBS!$A$2:$A$115,$A15) -> 26 | G15: =SUMIFS(WBS!$L$2:$L$115,WBS!$A$2:$A$115,$A15) -> 32 | H15: =SUM(D15:G15) -> 178 | I15: =IF($C$8=0,0,H15/$C$8) -> 0.055365474
A16: E02 | B16: Authentication, RBAC & Role Management | C16: =COUNTIF(WBS!$A$2:$A$115,A16) -> 13 | D16: =SUMIFS(WBS!$I$2:$I$115,WBS!$A$2:$A$115,$A16) -> 120 | E16: =SUMIFS(WBS!$J$2:$J$115,WBS!$A$2:$A$115,$A16) -> 144 | F16: =SUMIFS(WBS!$K$2:$K$115,WBS!$A$2:$A$115,$A16) -> 75 | G16: =SUMIFS(WBS!$L$2:$L$115,WBS!$A$2:$A$115,$A16) -> 0 | H16: =SUM(D16:G16) -> 339 | I16: =IF($C$8=0,0,H16/$C$8) -> 0.10544323
A17: E03 | B17: Admin Shell & Notifications | C17: =COUNTIF(WBS!$A$2:$A$115,A17) -> 5 | D17: =SUMIFS(WBS!$I$2:$I$115,WBS!$A$2:$A$115,$A17) -> 58 | E17: =SUMIFS(WBS!$J$2:$J$115,WBS!$A$2:$A$115,$A17) -> 26 | F17: =SUMIFS(WBS!$K$2:$K$115,WBS!$A$2:$A$115,$A17) -> 21 | G17: =SUMIFS(WBS!$L$2:$L$115,WBS!$A$2:$A$115,$A17) -> 0 | H17: =SUM(D17:G17) -> 105 | I17: =IF($C$8=0,0,H17/$C$8) -> 0.032659409
A18: E04 | B18: Master Data (Category, Brand, Warehouse, Lists) | C18: =COUNTIF(WBS!$A$2:$A$115,A18) -> 4 | D18: =SUMIFS(WBS!$I$2:$I$115,WBS!$A$2:$A$115,$A18) -> 52 | E18: =SUMIFS(WBS!$J$2:$J$115,WBS!$A$2:$A$115,$A18) -> 42 | F18: =SUMIFS(WBS!$K$2:$K$115,WBS!$A$2:$A$115,$A18) -> 22 | G18: =SUMIFS(WBS!$L$2:$L$115,WBS!$A$2:$A$115,$A18) -> 0 | H18: =SUM(D18:G18) -> 116 | I18: =IF($C$8=0,0,H18/$C$8) -> 0.036080871
A19: E05 | B19: Attributes | C19: =COUNTIF(WBS!$A$2:$A$115,A19) -> 3 | D19: =SUMIFS(WBS!$I$2:$I$115,WBS!$A$2:$A$115,$A19) -> 30 | E19: =SUMIFS(WBS!$J$2:$J$115,WBS!$A$2:$A$115,$A19) -> 26 | F19: =SUMIFS(WBS!$K$2:$K$115,WBS!$A$2:$A$115,$A19) -> 15 | G19: =SUMIFS(WBS!$L$2:$L$115,WBS!$A$2:$A$115,$A19) -> 0 | H19: =SUM(D19:G19) -> 71 | I19: =IF($C$8=0,0,H19/$C$8) -> 0.022083981
A20: E06 | B20: Product – Add Product Wizard | C20: =COUNTIF(WBS!$A$2:$A$115,A20) -> 16 | D20: =SUMIFS(WBS!$I$2:$I$115,WBS!$A$2:$A$115,$A20) -> 202 | E20: =SUMIFS(WBS!$J$2:$J$115,WBS!$A$2:$A$115,$A20) -> 98 | F20: =SUMIFS(WBS!$K$2:$K$115,WBS!$A$2:$A$115,$A20) -> 81 | G20: =SUMIFS(WBS!$L$2:$L$115,WBS!$A$2:$A$115,$A20) -> 0 | H20: =SUM(D20:G20) -> 381 | I20: =IF($C$8=0,0,H20/$C$8) -> 0.118507
A21: E07 | B21: Product – Product List | C21: =COUNTIF(WBS!$A$2:$A$115,A21) -> 6 | D21: =SUMIFS(WBS!$I$2:$I$115,WBS!$A$2:$A$115,$A21) -> 76 | E21: =SUMIFS(WBS!$J$2:$J$115,WBS!$A$2:$A$115,$A21) -> 68 | F21: =SUMIFS(WBS!$K$2:$K$115,WBS!$A$2:$A$115,$A21) -> 36 | G21: =SUMIFS(WBS!$L$2:$L$115,WBS!$A$2:$A$115,$A21) -> 0 | H21: =SUM(D21:G21) -> 180 | I21: =IF($C$8=0,0,H21/$C$8) -> 0.055987558
A22: E08 | B22: Product – Expire Product | C22: =COUNTIF(WBS!$A$2:$A$115,A22) -> 6 | D22: =SUMIFS(WBS!$I$2:$I$115,WBS!$A$2:$A$115,$A22) -> 46 | E22: =SUMIFS(WBS!$J$2:$J$115,WBS!$A$2:$A$115,$A22) -> 68 | F22: =SUMIFS(WBS!$K$2:$K$115,WBS!$A$2:$A$115,$A22) -> 30 | G22: =SUMIFS(WBS!$L$2:$L$115,WBS!$A$2:$A$115,$A22) -> 0 | H22: =SUM(D22:G22) -> 144 | I22: =IF($C$8=0,0,H22/$C$8) -> 0.044790047
A23: E09 | B23: Order Management | C23: =COUNTIF(WBS!$A$2:$A$115,A23) -> 8 | D23: =SUMIFS(WBS!$I$2:$I$115,WBS!$A$2:$A$115,$A23) -> 88 | E23: =SUMIFS(WBS!$J$2:$J$115,WBS!$A$2:$A$115,$A23) -> 112 | F23: =SUMIFS(WBS!$K$2:$K$115,WBS!$A$2:$A$115,$A23) -> 50 | G23: =SUMIFS(WBS!$L$2:$L$115,WBS!$A$2:$A$115,$A23) -> 0 | H23: =SUM(D23:G23) -> 250 | I23: =IF($C$8=0,0,H23/$C$8) -> 0.077760498
A24: E10 | B24: Vendor Management | C24: =COUNTIF(WBS!$A$2:$A$115,A24) -> 6 | D24: =SUMIFS(WBS!$I$2:$I$115,WBS!$A$2:$A$115,$A24) -> 68 | E24: =SUMIFS(WBS!$J$2:$J$115,WBS!$A$2:$A$115,$A24) -> 66 | F24: =SUMIFS(WBS!$K$2:$K$115,WBS!$A$2:$A$115,$A24) -> 35 | G24: =SUMIFS(WBS!$L$2:$L$115,WBS!$A$2:$A$115,$A24) -> 0 | H24: =SUM(D24:G24) -> 169 | I24: =IF($C$8=0,0,H24/$C$8) -> 0.052566096
A25: E11 | B25: Customer Management | C25: =COUNTIF(WBS!$A$2:$A$115,A25) -> 8 | D25: =SUMIFS(WBS!$I$2:$I$115,WBS!$A$2:$A$115,$A25) -> 56 | E25: =SUMIFS(WBS!$J$2:$J$115,WBS!$A$2:$A$115,$A25) -> 68 | F25: =SUMIFS(WBS!$K$2:$K$115,WBS!$A$2:$A$115,$A25) -> 33 | G25: =SUMIFS(WBS!$L$2:$L$115,WBS!$A$2:$A$115,$A25) -> 0 | H25: =SUM(D25:G25) -> 157 | I25: =IF($C$8=0,0,H25/$C$8) -> 0.048833593
A26: E12 | B26: CMS – Web Management & Media | C26: =COUNTIF(WBS!$A$2:$A$115,A26) -> 21 | D26: =SUMIFS(WBS!$I$2:$I$115,WBS!$A$2:$A$115,$A26) -> 258 | E26: =SUMIFS(WBS!$J$2:$J$115,WBS!$A$2:$A$115,$A26) -> 204 | F26: =SUMIFS(WBS!$K$2:$K$115,WBS!$A$2:$A$115,$A26) -> 113 | G26: =SUMIFS(WBS!$L$2:$L$115,WBS!$A$2:$A$115,$A26) -> 0 | H26: =SUM(D26:G26) -> 575 | I26: =IF($C$8=0,0,H26/$C$8) -> 0.17884914
... A28: E14 | B28: Non-Functional Hardening, Testing & Release | C28: =COUNTIF(WBS!$A$2:$A$115,A28) -> 7 | D28: =SUMIFS(WBS!$I$2:$I$115,WBS!$A$2:$A$115,$A28) -> 104 | E28: =SUMIFS(WBS!$J$2:$J$115,WBS!$A$2:$A$115,$A28) -> 124 | F28: =SUMIFS(WBS!$K$2:$K$115,WBS!$A$2:$A$115,$A28) -> 118 | G28: =SUMIFS(WBS!$L$2:$L$115,WBS!$A$2:$A$115,$A28) -> 36 | H28: =SUM(D28:G28) -> 382 | I28: =IF($C$8=0,0,H28/$C$8) -> 0.11881804
B29: TOTAL | C29: =SUM(C15:C28) -> 114 | D29: =SUM(D15:D28) -> 1272 | E29: =SUM(E15:E28) -> 1188 | F29: =SUM(F15:F28) -> 687 | G29: =SUM(G15:G28) -> 68 | H29: =SUM(H15:H28) -> 3215 | I29: =SUM(I15:I28) -> 1
A31: Effort by Priority
A32: Key | B32: Name | C32: Stories | D32: Frontend | E32: Backend | F32: QA | G32: DevOps | H32: Total | I32: % of total
A33: Must | B33: Must have (R1 – MVP) | C33: =COUNTIF(WBS!$F$2:$F$115,A33) -> 81 | D33: =SUMIFS(WBS!$I$2:$I$115,WBS!$F$2:$F$115,$A33) -> 872 | E33: =SUMIFS(WBS!$J$2:$J$115,WBS!$F$2:$F$115,$A33) -> 838 | F33: =SUMIFS(WBS!$K$2:$K$115,WBS!$F$2:$F$115,$A33) -> 469 | G33: =SUMIFS(WBS!$L$2:$L$115,WBS!$F$2:$F$115,$A33) -> 68 | H33: =SUM(D33:G33) -> 2247 | I33: =IF($C$8=0,0,H33/$C$8) -> 0.69891135
A34: Should | B34: Should have (R2) | C34: =COUNTIF(WBS!$F$2:$F$115,A34) -> 25 | D34: =SUMIFS(WBS!$I$2:$I$115,WBS!$F$2:$F$115,$A34) -> 300 | E34: =SUMIFS(WBS!$J$2:$J$115,WBS!$F$2:$F$115,$A34) -> 258 | F34: =SUMIFS(WBS!$K$2:$K$115,WBS!$F$2:$F$115,$A34) -> 174 | G34: =SUMIFS(WBS!$L$2:$L$115,WBS!$F$2:$F$115,$A34) -> 0 | H34: =SUM(D34:G34) -> 732 | I34: =IF($C$8=0,0,H34/$C$8) -> 0.22768274
A35: Could | B35: Could have (R3) | C35: =COUNTIF(WBS!$F$2:$F$115,A35) -> 8 | D35: =SUMIFS(WBS!$I$2:$I$115,WBS!$F$2:$F$115,$A35) -> 100 | E35: =SUMIFS(WBS!$J$2:$J$115,WBS!$F$2:$F$115,$A35) -> 92 | F35: =SUMIFS(WBS!$K$2:$K$115,WBS!$F$2:$F$115,$A35) -> 44 | G35: =SUMIFS(WBS!$L$2:$L$115,WBS!$F$2:$F$115,$A35) -> 0 | H35: =SUM(D35:G35) -> 236 | I35: =IF($C$8=0,0,H35/$C$8) -> 0.07340591
B36: TOTAL | C36: =SUM(C33:C35) -> 114 | D36: =SUM(D33:D35) -> 1272 | E36: =SUM(E33:E35) -> 1188 | F36: =SUM(F33:F35) -> 687 | G36: =SUM(G33:G35) -> 68 | H36: =SUM(H33:H35) -> 3215 | I36: =SUM(I33:I35) -> 1
A38: Notes
A39: 1. Estimates are for a mid-level engineer, include developer unit tests, and are accurate to about ±20%. QA hours include test design and execution.
A40: 2. Priority follows the SRS MoSCoW. Release: Must = R1 (MVP), Should = R2, Could = R3.
A41: 3. Frontend / Backend / QA / DevOps hours are shown separately; Developer Role(s) lists every role with hours on that story.
A42: 4. UI/UX design time is excluded because the FE design already exists. Findings F-01 to F-13 from the SRS are folded into the relevant stories.
A43: 5. Stories marked Dependency, provisional or scope to confirm (Category, Brand, Warehouse, Manage Users, Khalti/eSewa, non-supplied CMS pages, Policy/Security/Currency/Subscriber) need client confirmation.
A44: 6. Out of scope: customer storefront, Delivery Management, Suppliers, Delivery Rider and the Warehouse module beyond master data.
A45: 7. Change the blue inputs above to see duration update; all totals are formulas driven from the WBS sheet.

Sheet WBS
A1: Epic ID | B1: Epic | C1: Story ID | D1: User Story | E1: Acceptance Criteria | F1: Priority | G1: Release | H1: Developer Role(s) | I1: Frontend Hrs | J1: Backend Hrs | K1: QA Hrs | L1: DevOps Hrs | M1: Total Hrs | N1: SRS Reference | O1: Depends On
A2: E01 | B2: Project Setup & Platform Foundation | C2: US-1.01 | D2: As a developer, I want a Git repository with CI/CD and dev/staging/production environments so that code is built, tested and deployed consistently. | E2: 1. Merge to develop triggers build, lint, tests and auto-deploy to staging 2. Three environments run with separate configuration and secrets 3. Rollback to previous release works in under 15 minutes | F2: Must | G2: =IF(F2="Must","R1 – MVP",IF(F2="Should","R2","R3")) -> R1 – MVP | H2: Backend Dev, QA Engineer, DevOps Engineer | I2: 0 | J2: 4 | K2: 2 | L2: 24 | M2: =SUM(I2:L2) -> 30 | N2: NFR-04, NFR-10
A3: E01 | B3: Project Setup & Platform Foundation | C3: US-1.02 | D3: As a developer, I want solution architecture, database baseline, API conventions and OpenAPI documentation so that all modules follow one consistent technical design. | E3: 1. ERD covers all entities in SRS sections 5 2. REST conventions (pagination, error format, filtering) are documented and applied 3. Swagger/OpenAPI is generated and published for dev team | F3: Must | G3: =IF(F3="Must","R1 – MVP",IF(F3="Should","R2","R3")) -> R1 – MVP | H3: Backend Dev, QA Engineer | I3: 0 | J3: 28 | K3: 4 | L3: 0 | M3: =SUM(I3:L3) -> 32 | N3: SRS §5, NFR-10
A4: E01 | B4: Project Setup & Platform Foundation | C4: US-1.03 | D4: As a frontend developer, I want a React app scaffold with design tokens and a reusable component library (table toolbar, modal, upload zone, toast, breadcrumb, status toggle) so that every screen looks and behaves consistently. | E4: 1. Purple theme, typography and spacing tokens match the FE design 2. Components are documented in Storybook (or equivalent) 3. Table toolbar supports search, filter, sort and primary action slots | F4: Must | G4: =IF(F4="Must","R1 – MVP",IF(F4="Should","R2","R3")) -> R1 – MVP | H4: Frontend Dev, QA Engineer | I4: 44 | J4: 0 | K4: 6 | L4: 0 | M4: =SUM(I4:L4) -> 50 | N4: FR-GLB-06, NFR-05 | O4: 1.01
A5: E01 | B5: Project Setup & Platform Foundation | C5: US-1.04 | D5: As a platform operator, I want a file storage service with upload API, type/size validation and malware scan so that products, vendors and CMS files are stored securely. | E5: 1. Uploads accept only allowed types and sizes and are renamed on storage 2. Infected or invalid files are rejected with a clear error 3. Returned file has URL, path, MIME type, extension and size | F5: Must | G5: =IF(F5="Must","R1 – MVP",IF(F5="Should","R2","R3")) -> R1 – MVP | H5: Backend Dev, QA Engineer, DevOps Engineer | I5: 0 | J5: 24 | K5: 8 | L5: 8 | M5: =SUM(I5:L5) -> 40 | N5: FR-MED-05, NFR-02 | O5: 1.01
A6: E01 | B6: Project Setup & Platform Foundation | C6: US-1.05 | D6: As an admin, I want a central audit log service so that create, update, delete and status changes are traceable. | E6: 1. Each audited action stores user, entity, action, before/after values, IP and timestamp 2. Audit entries cannot be edited or deleted from the UI 3. Logs are retained for 12 months | F6: Must | G6: =IF(F6="Must","R1 – MVP",IF(F6="Should","R2","R3")) -> R1 – MVP | H6: Backend Dev, QA Engineer | I6: 0 | J6: 20 | K6: 6 | L6: 0 | M6: =SUM(I6:L6) -> 26 | N6: NFR-08, BR-08 | O6: 1.02
A7: E02 | B7: Authentication, RBAC & Role Management | C7: US-2.01 | D7: As an admin user, I want to log in and out securely with a session timeout so that only authorised staff access the panel. | E7: 1. Valid credentials open the dashboard; invalid credentials show an error 2. Session expires after configured inactivity and redirects to login 3. Passwords are hashed; brute-force attempts are throttled | F7: Must | G7: =IF(F7="Must","R1 – MVP",IF(F7="Should","R2","R3")) -> R1 – MVP | H7: Frontend Dev, Backend Dev, QA Engineer | I7: 12 | J7: 20 | K7: 8 | L7: 0 | M7: =SUM(I7:L7) -> 40 | N7: Dependency (auth out of SRS scope) | O7: 1.02
A8: E02 | B8: Authentication, RBAC & Role Management | C8: US-2.02 | D8: As a super admin, I want permissions enforced on both menu and API so that users see and do only what their role allows. | E8: 1. Menu items and buttons without permission are hidden 2. API returns 403 for unauthorised calls even if the UI is bypassed 3. Permission changes apply on next request or login | F8: Must | G8: =IF(F8="Must","R1 – MVP",IF(F8="Should","R2","R3")) -> R1 – MVP | H8: Frontend Dev, Backend Dev, QA Engineer | I8: 12 | J8: 24 | K8: 10 | L8: 0 | M8: =SUM(I8:L8) -> 46 | N8: FR-GLB-05, NFR-01 | O8: 2.10
A9: E02 | B9: Authentication, RBAC & Role Management | C9: US-2.03 | D9: As an admin, I want to view and search all roles in a table so that I can find and manage roles quickly. | E9: 1. Table shows S.N, Role Name, Description, Status toggle and view/edit/delete icons 2. Search filters by name and description as I type 3. Empty result shows "No roles found" | F9: Must | G9: =IF(F9="Must","R1 – MVP",IF(F9="Should","R2","R3")) -> R1 – MVP | H9: Frontend Dev, Backend Dev, QA Engineer | I9: 12 | J9: 8 | K9: 6 | L9: 0 | M9: =SUM(I9:L9) -> 26 | N9: FR-ROL-01, 02 | O9: 1.03
A10: E02 | B10: Authentication, RBAC & Role Management | C10: US-2.04 | D10: As an admin, I want to add a role with name and description so that new staff types can be created. | E10: 1. Role Name is required, unique (case-insensitive), 2–50 characters 2. Description is optional, up to 255 characters 3. New role is Active and appears in the list without page reload | F10: Must | G10: =IF(F10="Must","R1 – MVP",IF(F10="Should","R2","R3")) -> R1 – MVP | H10: Frontend Dev, Backend Dev, QA Engineer | I10: 8 | J10: 8 | K10: 5 | L10: 0 | M10: =SUM(I10:L10) -> 21 | N10: FR-ROL-03 | O10: 2.03
A11: E02 | B11: Authentication, RBAC & Role Management | C11: US-2.05 | D11: As an admin, I want to edit a role so that role details stay correct. | E11: 1. Dialog pre-fills current name and description 2. Same validation as Add applies 3. Save updates the table row and shows a success toast | F11: Must | G11: =IF(F11="Must","R1 – MVP",IF(F11="Should","R2","R3")) -> R1 – MVP | H11: Frontend Dev, Backend Dev, QA Engineer | I11: 6 | J11: 6 | K11: 4 | L11: 0 | M11: =SUM(I11:L11) -> 16 | N11: FR-ROL-04 | O11: 2.03
A12: E02 | B12: Authentication, RBAC & Role Management | C12: US-2.06 | D12: As an admin, I want to view role details in a read-only dialog so that I can check a role without editing it. | E12: 1. Eye icon opens dialog with icon, name, ACTIVE/INACTIVE badge and description 2. Dialog closes with the x icon or Esc | F12: Must | G12: =IF(F12="Must","R1 – MVP",IF(F12="Should","R2","R3")) -> R1 – MVP | H12: Frontend Dev, Backend Dev, QA Engineer | I12: 4 | J12: 2 | K12: 2 | L12: 0 | M12: =SUM(I12:L12) -> 8 | N12: FR-ROL-05 | O12: 2.03
A13: E02 | B13: Authentication, RBAC & Role Management | C13: US-2.07 | D13: As an admin, I want to delete a role after confirmation so that unused roles are removed. | E13: 1. Confirmation quotes the role name and states the action cannot be undone 2. A role assigned to users cannot be deleted; message shows the user count 3. Successful delete removes the row and logs an audit entry | F13: Must | G13: =IF(F13="Must","R1 – MVP",IF(F13="Should","R2","R3")) -> R1 – MVP | H13: Frontend Dev, Backend Dev, QA Engineer | I13: 6 | J13: 8 | K13: 5 | L13: 0 | M13: =SUM(I13:L13) -> 19 | N13: FR-ROL-06, 07, BR-03 | O13: 2.03
A14: E02 | B14: Authentication, RBAC & Role Management | C14: US-2.08 | D14: As a super admin, I want the Admin role to be protected so that the system can never lose full access. | E14: 1. Admin cannot be deleted or deactivated from UI or API 2. Admin permissions cannot be reduced | F14: Must | G14: =IF(F14="Must","R1 – MVP",IF(F14="Should","R2","R3")) -> R1 – MVP | H14: Frontend Dev, Backend Dev, QA Engineer | I14: 2 | J14: 6 | K14: 3 | L14: 0 | M14: =SUM(I14:L14) -> 11 | N14: FR-ROL-08, BR-02 | O14: 2.03
A15: E02 | B15: Authentication, RBAC & Role Management | C15: US-2.09 | D15: As an admin, I want to activate or deactivate a role with a toggle so that I can pause a role without deleting it. | E15: 1. Toggle updates status immediately with a toast 2. Inactive roles cannot be assigned to new users 3. Behaviour for existing users is applied as confirmed by the client (open question) | F15: Must | G15: =IF(F15="Must","R1 – MVP",IF(F15="Should","R2","R3")) -> R1 – MVP | H15: Frontend Dev, Backend Dev, QA Engineer | I15: 4 | J15: 4 | K15: 3 | L15: 0 | M15: =SUM(I15:L15) -> 11 | N15: FR-ROL-09 | O15: 2.03
... A115: E14 | B115: Non-Functional Hardening, Testing & Release | C115: US-14.07 | D115: As an operator, I want production deployment, monitoring, backups, runbook and admin training material so that the system is supportable. | E115: 1. Monitoring and alerts live; daily backups tested by restore 2. Runbook and user guide delivered | F115: Must | G115: =IF(F115="Must","R1 – MVP",IF(F115="Should","R2","R3")) -> R1 – MVP | H115: Backend Dev, QA Engineer, DevOps Engineer | I115: 0 | J115: 6 | K115: 4 | L115: 24 | M115: =SUM(I115:L115) -> 34 | N115: NFR-04 | O115: 14.06
D116: TOTAL | I116: =SUM(I2:I115) -> 1272 | J116: =SUM(J2:J115) -> 1188 | K116: =SUM(K2:K115) -> 687 | L116: =SUM(L2:L115) -> 68 | M116: =SUM(M2:M115) -> 3215
